<annotation>
	<folder>chihuahua_-_Google_Penelusuran</folder>
	<filename>Chihuahua (99).jpg</filename>
	<path>C:\Users\Asus\Downloads\Anjing\chihuahua_-_Google_Penelusuran\Chihuahua (99).jpg</path>
	<source>
		<database>Unknown</database>
	</source>
	<size>
		<width>202</width>
		<height>249</height>
		<depth>3</depth>
	</size>
	<segmented>0</segmented>
	<object>
		<name>Bulldog</name>
		<pose>Unspecified</pose>
		<truncated>1</truncated>
		<difficult>0</difficult>
		<bndbox>
			<xmin>27</xmin>
			<ymin>6</ymin>
			<xmax>195</xmax>
			<ymax>249</ymax>
		</bndbox>
	</object>
</annotation>
